[
	{
		"inputs": [
			{
				"internalType": "address",
				"name": "newOwner",
				"type": "address"
			}
		],
		"name": "changeOwner",
		"outputs": [],
		"stateMutability": "nonpayable",
		"type": "function"
	},
	{
		"inputs": [
			{
				"internalType": "address",
				"name": "tokenAddress",
				"type": "address"
			},
			{
				"internalType": "uint256",
				"name": "amount",
				"type": "uint256"
			}
		],
		"name": "claimNewToken",
		"outputs": [],
		"stateMutability": "payable",
		"type": "function"
	},
	{
		"inputs": [
			{
				"internalType": "address",
				"name": "user",
				"type": "address"
			}
		],
		"name": "claimTokens",
		"outputs": [],
		"stateMutability": "payable",
		"type": "function"
	},
	{
		"inputs": [],
		"name": "deposit",
		"outputs": [],
		"stateMutability": "payable",
		"type": "function"
	},
	{
		"inputs": [
			{
				"internalType": "address",
				"name": "_MLENS",
				"type": "address"
			},
			{
				"internalType": "address",
				"name": "_EDNAMODE",
				"type": "address"
			}
		],
		"stateMutability": "nonpayable",
		"type": "constructor"
	},
	{
		"anonymous": false,
		"inputs": [
			{
				"indexed": true,
				"internalType": "address",
				"name": "sender",
				"type": "address"
			},
			{
				"indexed": false,
				"internalType": "uint256",
				"name": "amount",
				"type": "uint256"
			},
			{
				"indexed": false,
				"internalType": "address",
				"name": "tokenAddress",
				"type": "address"
			}
		],
		"name": "TokensAdded",
		"type": "event"
	},
	{
		"inputs": [
			{
				"internalType": "address",
				"name": "_Sender",
				"type": "address"
			}
		],
		"name": "updateAddress",
		"outputs": [],
		"stateMutability": "nonpayable",
		"type": "function"
	},
	{
		"inputs": [
			{
				"internalType": "uint256",
				"name": "_Gmeld",
				"type": "uint256"
			},
			{
				"internalType": "uint256",
				"name": "_mlense",
				"type": "uint256"
			},
			{
				"internalType": "uint256",
				"name": "_echana",
				"type": "uint256"
			}
		],
		"name": "updateTokenValue",
		"outputs": [],
		"stateMutability": "nonpayable",
		"type": "function"
	},
	{
		"inputs": [
			{
				"internalType": "uint256",
				"name": "amount",
				"type": "uint256"
			}
		],
		"name": "withdraw",
		"outputs": [],
		"stateMutability": "nonpayable",
		"type": "function"
	},
	{
		"stateMutability": "payable",
		"type": "receive"
	},
	{
		"inputs": [],
		"name": "claimInterval",
		"outputs": [
			{
				"internalType": "uint256",
				"name": "",
				"type": "uint256"
			}
		],
		"stateMutability": "view",
		"type": "function"
	},
	{
		"inputs": [],
		"name": "contractBalance",
		"outputs": [
			{
				"internalType": "uint256",
				"name": "",
				"type": "uint256"
			}
		],
		"stateMutability": "view",
		"type": "function"
	},
	{
		"inputs": [],
		"name": "EchanamodeTokenValue",
		"outputs": [
			{
				"internalType": "uint256",
				"name": "",
				"type": "uint256"
			}
		],
		"stateMutability": "view",
		"type": "function"
	},
	{
		"inputs": [],
		"name": "EDNAMODE",
		"outputs": [
			{
				"internalType": "contract IERC20",
				"name": "",
				"type": "address"
			}
		],
		"stateMutability": "view",
		"type": "function"
	},
	{
		"inputs": [],
		"name": "getTokenValues",
		"outputs": [
			{
				"internalType": "uint256",
				"name": "",
				"type": "uint256"
			},
			{
				"internalType": "uint256",
				"name": "",
				"type": "uint256"
			},
			{
				"internalType": "uint256",
				"name": "",
				"type": "uint256"
			}
		],
		"stateMutability": "view",
		"type": "function"
	},
	{
		"inputs": [],
		"name": "GmeldTokenValue",
		"outputs": [
			{
				"internalType": "uint256",
				"name": "",
				"type": "uint256"
			}
		],
		"stateMutability": "view",
		"type": "function"
	},
	{
		"inputs": [
			{
				"internalType": "address",
				"name": "",
				"type": "address"
			}
		],
		"name": "lastClaimed",
		"outputs": [
			{
				"internalType": "uint256",
				"name": "",
				"type": "uint256"
			}
		],
		"stateMutability": "view",
		"type": "function"
	},
	{
		"inputs": [],
		"name": "MLENS",
		"outputs": [
			{
				"internalType": "contract IERC20",
				"name": "",
				"type": "address"
			}
		],
		"stateMutability": "view",
		"type": "function"
	},
	{
		"inputs": [],
		"name": "MlenseTokenValue",
		"outputs": [
			{
				"internalType": "uint256",
				"name": "",
				"type": "uint256"
			}
		],
		"stateMutability": "view",
		"type": "function"
	},
	{
		"inputs": [],
		"name": "owner",
		"outputs": [
			{
				"internalType": "address",
				"name": "",
				"type": "address"
			}
		],
		"stateMutability": "view",
		"type": "function"
	}
]